hklahklab
