Metadata-Version: 1.0
Name: hklabhklab
Version: 0.0.3
Summary: isoweek calculation and so on
Home-page: http://github.com/kimhyokwan/hklabhklab
Author: kimhyokwan
Author-email: haiteam@kopo.ac.kr
License: MIT
Keywords: calendar,isoweek,listsum
Platform: UNKNOWN
